setup.py
./__init__.py
./example.py
./router.py
WSGIRouter.egg-info/PKG-INFO
WSGIRouter.egg-info/SOURCES.txt
WSGIRouter.egg-info/dependency_links.txt
WSGIRouter.egg-info/requires.txt
WSGIRouter.egg-info/top_level.txt
WSGIRouter.egg-info/zip-safe