Metadata-Version: 1.0
Name: WSGIRouter
Version: 0.4
Summary: Tiny library for WebOb to manage URL and Request routing correctly without many dependencies
Home-page: https://github.com/samalba/wsgirouter
Author: Samuel Alba
Author-email: sam.alba@gmail.com
License: MIT
Keywords: wsgi request web http
Platform: UNKNOWN
